README.md
setup.py
BusyBox/FactoryUtils.py
BusyBox/ServiceBox.py
BusyBox/_Types.py
BusyBox/__init__.py
BusyBox.egg-info/PKG-INFO
BusyBox.egg-info/SOURCES.txt
BusyBox.egg-info/dependency_links.txt
BusyBox.egg-info/top_level.txt
test/TestInjectorDemo.py
test/test_Injector.py