Metadata-Version: 2.1
Name: BusyBox
Version: 1.0.3
Summary: 
Home-page: https://github.com/AngelovLee/BusyBox
Author: Jaysen Leo
Author-email: jaysenleo@163.com
Maintainer: Jaysen Leo
Maintainer-email: jaysenleo@163.com
License: MIT License
Keywords: inject,depend,invoke,BusyBox
Platform: linux
Platform: windows
Classifier: Development Status :: 4 - Beta
Classifier: Operating System :: OS Independent
Classifier: Intended Audience :: Developers
Classifier: License :: OSI Approved :: MIT License
Classifier: Programming Language :: Python
Classifier: Programming Language :: Python :: Implementation
Classifier: Programming Language :: Python :: 3.6
Classifier: Programming Language :: Python :: 3.7
Classifier: Programming Language :: Python :: 3.8
Classifier: Programming Language :: Python :: 3.9
Classifier: Programming Language :: Python :: 3.10
Classifier: Topic :: Software Development :: Libraries
